oneparams/__init__.py
oneparams/config.py
oneparams/one.py
oneparams/reset.py
oneparams/utils.py
oneparams/api/__init__.py
oneparams/api/base.py
oneparams/api/base_diff.py
oneparams/api/cards.py
oneparams/api/cidade.py
oneparams/api/client.py
oneparams/api/colaborador.py
oneparams/api/commission.py
oneparams/api/conta.py
oneparams/api/fabricante.py
oneparams/api/forma_pagamento.py
oneparams/api/fornecedor.py
oneparams/api/grupo_produto.py
oneparams/api/gservs.py
oneparams/api/linha_produto.py
oneparams/api/login.py
oneparams/api/operadora.py
oneparams/api/perfils.py
oneparams/api/produto.py
oneparams/api/profissao.py
oneparams/api/servicos.py
oneparams/api/submodule.py
oneparams/excel/__init__.py
oneparams/excel/card.py
oneparams/excel/checks.py
oneparams/excel/cliente.py
oneparams/excel/colaborador.py
oneparams/excel/comissao.py
oneparams/excel/excel.py
oneparams/excel/produto.py
oneparams/excel/servicos.py
oneparams-0.5.0.0.dist-info/LICENSE
oneparams-0.5.0.0.dist-info/METADATA
oneparams-0.5.0.0.dist-info/WHEEL
oneparams-0.5.0.0.dist-info/entry_points.txt
oneparams-0.5.0.0.dist-info/top_level.txt
oneparams-0.5.0.0.dist-info/RECORD
