Metadata-Version: 2.1
Name: oneparams
Version: 0.5.0.0
Summary: One System Parametrizer
Home-page: https://github.com/exebixel/oneparams
Author: exebixel
Author-email: ezequielnat7@gmail.com
Classifier: Operating System :: OS Independent
Classifier: Environment :: Console
Classifier: Programming Language :: Python
Classifier: Programming Language :: Python :: 3
Classifier: Programming Language :: Python :: 3.7
Classifier: Programming Language :: Python :: 3.8
Requires-Python: >=3.7
License-File: LICENSE
Requires-Dist: requests
Requires-Dist: pandas (>=1.4.0)
Requires-Dist: urllib3
Requires-Dist: xlrd
Requires-Dist: openpyxl
Requires-Dist: click (>=7.0)
Requires-Dist: alive-progress (>=2.4.1)
